{"name":"App Watcher","tagline":"App Watcher for Android helps you to follow updates of applications in Play Store that are not installed currently on your device.","body":"App Watcher for Android\r\n=======================\r\n\r\nApp Watcher helps you to receive notifications about updates for application from Play Store even the app is not installed currently on your device\r\n\r\nFeatures:\r\n\r\n* Search and add app from Play Market to watch list\r\n* Manual and automatic updates\r\n* Quick shortcut to see what's new in app\r\n* Share application\r\n\r\n[Google Play Store][1]\r\n\r\n## Implementation highlights\r\n\r\n* SQLite database - store the data\r\n* ContentProvider - access to the data\r\n* AccountManager - access to 3rd party account on device\r\n* Android's backup service\r\n* SyncAdapter & AccountAuthenticator - create android account for synchronization\r\n* Fragments\r\n* LoadManager\r\n* ActionBar\r\n* NotificationCompat\r\n* ShareCompat\r\n\r\n## Dependencies\r\n * SherlockActionBar library \r\n\r\n## 3rd party components\r\n * [SherlockActionBar library] [4]\r\n * [Adroid Market Api][2]\r\n * [CommonsWare EndlessAdapter][3]\r\n \r\n## Author\r\n\r\nAlex Gavrishev, 2012-2014\r\n \r\n [1]: https://play.google.com/store/apps/developer?id=Alex+Gavrishev\r\n [2]: http://code.google.com/p/android-market-api/\r\n [3]: https://github.com/commonsguy/cwac-endless\r\n [4]: http://actionbarsherlock.com/\r\n","google":"UA-1633675-3","note":"Don't delete this file! It's used internally to help with page regeneration."}